verysimplemoduleaupmanyu1/__init__.py
verysimplemoduleaupmanyu1/add.py
verysimplemoduleaupmanyu1/subtract.py
verysimplemoduleaupmanyu1/extras/__init__.py
verysimplemoduleaupmanyu1/extras/divide.py
verysimplemoduleaupmanyu1/extras/multiply.py
verysimplemoduleaupmanyu1-0.0.1.dist-info/METADATA
verysimplemoduleaupmanyu1-0.0.1.dist-info/WHEEL
verysimplemoduleaupmanyu1-0.0.1.dist-info/top_level.txt
verysimplemoduleaupmanyu1-0.0.1.dist-info/RECORD
